[
  {
    "number": 1,
    "q": "두 개의 서로 다른 금속의 접속점에 온도차를 주면 기전력이 생기는 현상은?",
    "c1": "홀 효과",
    "c2": "줄 효과",
    "c3": "압전기 효과",
    "c4": "제벡 효과",
    "has_image": false
  },
  {
    "number": 2,
    "q": "다음 중에서 자석의 일반적인 성질에 대한 설명으로 틀린 것은?",
    "c1": "N극과 S극이 있다.",
    "c2": "자력선은 N극에서 나와 S극으로 향한다.",
    "c3": "자력이 강할수록 자기력선의 수가 많다.",
    "c4": "자석을 고온이 되면 자력이 증가한다.",
    "has_image": false
  },
  {
    "number": 3,
    "q": "자체 인덕턴스 2[H]의 코일에 25[J]의 에너지가 저장되어 있다면 코일에 흐르는 전류는?",
    "c1": "2[A]",
    "c2": "3[A]",
    "c3": "4[A]",
    "c4": "5[A]",
    "has_image": false
  },
  {
    "number": 4,
    "q": "비정현파의 실효값을 나타낸 것은?",
    "c1": "최대파의 실효값",
    "c2": "각 고조파의 실효값의 합",
    "c3": "각 고조파의 실효값 제곱의 제곱근",
    "c4": "각 고조파의 실효값과 제곱의 합의 제곱근",
    "has_image": false
  },
  {
    "number": 5,
    "q": "기전력 1.5[V], 내부저항 0.2[$\\Omega$]인 건전지 5개를 직렬접속하고 감수하여 단자사이전류를 측정하면 몇 [A]인가?",
    "c1": "1.5[A]",
    "c2": "2.5[A]",
    "c3": "5[A]",
    "c4": "7.5[A]",
    "has_image": false
  },
  {
    "number": 6,
    "q": "브리지 회로에서 미지의 인덕턴스 $L_x$를 구하면?",
    "c1": "$L_1$",
    "c2": "$L_4$",
    "c3": "$\\dfrac{L_1 L_4}{L_3}$",
    "c4": "$\\dfrac{L_1 L_3}{L_4}$",
    "has_image": true
  },
  {
    "number": 7,
    "q": "$R_1$, $R_2$, $R_3$의 저항 3개를 직렬 결속했을 때의 합성 저항 값은?",
    "c1": "$R = R_1 + R_2 + R_3$",
    "c2": "$R = R_2 + R_3$",
    "c3": "$R = \\dfrac{1}{R_1} + \\dfrac{1}{R_2} + \\dfrac{1}{R_3}$",
    "c4": "$R = R_1 \\times R_2 \\times R_3$",
    "has_image": true
  },
  {
    "number": 8,
    "q": "그림과 같은 회로에서 3개의 콘덴서를 합한 전체 합성 커패시턴스 C[F]의 값이 되는가?",
    "c1": "35[C]",
    "c2": "3[C]",
    "c3": "$\\dfrac{4}{3}$[C]",
    "c4": "$\\dfrac{3}{4}$[C]",
    "has_image": true
  },
  {
    "number": 9,
    "q": "같은 온도 200[$\\Omega$]의 구리 P와 300[$\\Omega$]의 구리 S를 병렬 연결한 것을 P에 1[A]의 전류를 흘림 때 S에 네오선은 자극이 몇 $\\times 10^{-1}$[Wb]이었다면 이 네오선의 자극의 값은?",
    "c1": "0.12[H]",
    "c2": "0.12[mH]",
    "c3": "12[H]",
    "c4": "12[mH]",
    "has_image": false
  },
  {
    "number": 10,
    "q": "다음 중 쿨롱원을 나타낸 것은?",
    "c1": "경로길",
    "c2": "단극길",
    "c3": "광국고",
    "c4": "편극고",
    "has_image": false
  },
  {
    "number": 11,
    "q": "플레밍의 오른손 법칙에서 손가락이 가리키는 방향은?",
    "c1": "운동 방향",
    "c2": "자속밀도의 방향",
    "c3": "유도기전력의 방향",
    "c4": "자력선의 방향",
    "has_image": false
  },
  {
    "number": 12,
    "q": "2[$\\mu$C]의 전기장이 이동을 하여 10[V]의 일을 하였을 때 두 점 사이의 전위차는 몇 [V]인가?",
    "c1": "0.2[V]",
    "c2": "0.5[V]",
    "c3": "5[V]",
    "c4": "20[V]",
    "has_image": false
  },
  {
    "number": 13,
    "q": "다음 중 1[cal]과 같은 것은?",
    "c1": "1[cal]",
    "c2": "1[W $\\cdot$ 1]",
    "c3": "1[kg $\\cdot$ m]",
    "c4": "1[N $\\cdot$ m]",
    "has_image": false
  },
  {
    "number": 14,
    "q": "\"회로에 흐르는 전류의 크기는 저항에 (ㅇ) 하고, 가해진 전압에 (ㅇ) 한다.\" 의 알맞은 내용을 바르게 나열한 것은?",
    "c1": "비례, 반비례",
    "c2": "비례, 비례",
    "c3": "반비례, 반비례",
    "c4": "반비례, 비례",
    "has_image": false
  },
  {
    "number": 15,
    "q": "진공 중에서 같은 크기의 두 자극이 1[m] 거리에 있을 때 그 작용하는 힘은? (단, 자극의 세기는 1[Wb]이다.)",
    "c1": "$6.33 \\times 10^4$[N]",
    "c2": "$8.33 \\times 10^4$[N]",
    "c3": "$9.33 \\times 10^4$[N]",
    "c4": "$9.09 \\times 10^4$[N]",
    "has_image": false
  },
  {
    "number": 16,
    "q": "각속도 $\\omega = 300$[rad/sec]인 사인 교류의 주파수[Hz]는 얼마인가?",
    "c1": "$\\dfrac{70}{\\pi}$",
    "c2": "$\\dfrac{150}{\\pi}$",
    "c3": "$\\dfrac{180}{\\pi}$",
    "c4": "$\\dfrac{360}{\\pi}$",
    "has_image": false
  },
  {
    "number": 17,
    "q": "$C_1$, $C_2$를 직렬로 접속한 회로에 $L_1$을 병렬로 접속하였다. 이 회로의 합성 정전용량[F]은?",
    "c1": "$C_1 + \\dfrac{C_1}{C_2}$",
    "c2": "$\\dfrac{C_1 C_2}{C_1 + C_2}$",
    "c3": "$C_1 + C_1 C_2$",
    "c4": "$C_1 + \\dfrac{C_1 C_2}{C_1 + C_2}$",
    "has_image": true
  },
  {
    "number": 18,
    "q": "$Z_a = 5 + j3$[이고 $Z_b = 7 - j3$[$\\Omega$]이 직렬 연결된 회로에 V=36[V]을 가한 경우의 전류 I[A]는?",
    "c1": "1[A]",
    "c2": "3[A]",
    "c3": "5[A]",
    "c4": "6[A]",
    "has_image": false
  },
  {
    "number": 19,
    "q": "10[A]의 전류로 6시간 충전할 수 있는 축전지의 용량은?",
    "c1": "2[Ah]",
    "c2": "15[Ah]",
    "c3": "30[Ah]",
    "c4": "60[Ah]",
    "has_image": false
  },
  {
    "number": 20,
    "q": "3상 교류를 Y 결선 하였을 때 선전압과 상전압, 선전류와 상전류의 관계를 바르게 나타낸 것은?",
    "c1": "상전압 = $\\sqrt{3}$ 선전압",
    "c2": "선전류 = $\\sqrt{3}$ 상전류",
    "c3": "상전류 = $\\sqrt{3}$ 선전류",
    "c4": "선전압 = $\\sqrt{3}$ 상전압",
    "has_image": false
  },
  {
    "number": 21,
    "q": "직류기의 전기자 철심을 규소 강판으로 성층하여 만드는 이유는?",
    "c1": "기계적 철손",
    "c2": "마찰을 줄이기 위해",
    "c3": "기계의 중량을 줄이기 위해",
    "c4": "철손을 줄이기 위해",
    "has_image": false
  },
  {
    "number": 22,
    "q": "정격전압 250[V], 정격출력 50[kW]의 외분권 복권 발전기가 있다. 분권자 저항이 25[$\\Omega$]일 때 전기자 전류[A]는?",
    "c1": "100[A]",
    "c2": "210[A]",
    "c3": "2000[A]",
    "c4": "2010[A]",
    "has_image": false
  },
  {
    "number": 23,
    "q": "다음 중 발전기를 축전하는 것은?",
    "c1": "권선단인덕터법",
    "c2": "전류변성기법",
    "c3": "히이스 본 브리지법",
    "c4": "3전류계법",
    "has_image": false
  },
  {
    "number": 24,
    "q": "그림과 같은 회로의 기동 단상 유도 전동기의 역회전 시키기 위한 방법은?",
    "c1": "콤심성 스위치를 거꾸로 또는 뒤로 한다.",
    "c2": "기동권선의 극수 바꿔 다시 감는다. 또는 갈아서 접속할 수 있는 기동권선의 단자결손을 바꾼다. 또는 운전권선의 단자결손을 바꾼다.",
    "c3": "기동권선의 단자결손을 바꾼다. 또는 운전권선의 단자결손을 바꾼다.",
    "c4": "보조권 단결선을 바꾼다.",
    "has_image": true
  },
  {
    "number": 25,
    "q": "반파 정류회로에서 변압기 2차 전압의 실효값 E[V]라면 직류 전압 평균값은[V]는?",
    "c1": "$\\dfrac{E}{\\pi}$",
    "c2": "$\\dfrac{\\sqrt{2}E}{\\pi}$",
    "c3": "$\\dfrac{2\\sqrt{2}E}{\\pi}$",
    "c4": "$\\dfrac{E}{2\\pi}$",
    "has_image": false
  },
  {
    "number": 26,
    "q": "농형 유도 전동기의 기동법이 아닌 것은?",
    "c1": "기동보상기법",
    "c2": "Y-$\\Delta$ 기동법",
    "c3": "직입 2차저항기동법",
    "c4": "기동보상기법",
    "has_image": false
  },
  {
    "number": 27,
    "q": "실리콘 제어 정류기(SCR)에 대한 설명으로 틀린 것은?",
    "c1": "반영구적이므로 수명이 길다.",
    "c2": "제어 전류가 필요 없다.",
    "c3": "속도 제어가 용이하다.",
    "c4": "소형이며 중량이 가볍다.",
    "has_image": false
  },
  {
    "number": 28,
    "q": "변압기의 주파수와 권선비에 영향을 끼치는 것은?",
    "c1": "주파수에 반비례",
    "c2": "주파수와 권선비에 비례",
    "c3": "권선비에 반비례",
    "c4": "주파수에 비례",
    "has_image": false
  },
  {
    "number": 29,
    "q": "동기 전동기의 전기자 전류가 전류가 최소일 때 역률은?",
    "c1": "0.5",
    "c2": "0.707",
    "c3": "0.866",
    "c4": "1.0",
    "has_image": false
  },
  {
    "number": 30,
    "q": "동기 발전기의 병렬 운전 조건이 아닌 것은?",
    "c1": "기전력의 크기가 같을 것",
    "c2": "기전력의 위상이 같을 것",
    "c3": "기전력의 주파수가 같을 것",
    "c4": "기전력의 용량이 같을 것",
    "has_image": false
  },
  {
    "number": 31,
    "q": "부족출력 계전기의 설치 위치는?",
    "c1": "변압기 주 탱크 내부",
    "c2": "변압기의 고압측 부싱",
    "c3": "본체와 콘서베이터 사이",
    "c4": "콘서베이터 위",
    "has_image": false
  },
  {
    "number": 32,
    "q": "직류 전동기의 속도제어 방법이 아닌 것은?",
    "c1": "전압제어",
    "c2": "계자제어",
    "c3": "저항제어",
    "c4": "플리커제어",
    "has_image": false
  },
  {
    "number": 33,
    "q": "무산성 발전기에 불꽃도는?",
    "c1": "직류 대용량기",
    "c2": "저속 소용량기",
    "c3": "교류 대용량기",
    "c4": "교류 소용량기",
    "has_image": false
  },
  {
    "number": 34,
    "q": "전력계통에 연속되어 있는 변압기나 발전기가 충전 용량으로 인한 충전전류을 보상하기 위한 것은?",
    "c1": "배전용 변압기",
    "c2": "등기 발전기",
    "c3": "유도용 전동기",
    "c4": "동기 조상기",
    "has_image": false
  },
  {
    "number": 35,
    "q": "전력변압기의 규약 효율은?",
    "c1": "(출력/입력)$\\times$100[%]",
    "c2": "(출력/(출력+손실))$\\times$100[%]",
    "c3": "(출력/(입력-손실))$\\times$100[%]",
    "c4": "(입력+손실)/(입력)$\\times$100[%]",
    "has_image": false
  },
  {
    "number": 36,
    "q": "회전자 입력을 $P_1$, 슬립을 s 할 때 3상 유도 전동기의 기계적 출력의 관계식은?",
    "c1": "$sP_1$",
    "c2": "$(1-s)P_1$",
    "c3": "$\\dfrac{s}{P_1}$",
    "c4": "$P_1 \\cdot P_2$",
    "has_image": false
  },
  {
    "number": 37,
    "q": "무부하에서 110[V]이다는 분권 발전기의 전압 변동률은 외부 전압이 100[V]이면 전압 변동률은 몇 [%]인가?",
    "c1": "110.2",
    "c2": "112.3",
    "c3": "122.5",
    "c4": "125.3",
    "has_image": false
  },
  {
    "number": 38,
    "q": "5.5[kW], 200[V] 유도전동기의 전전압 기동시의 기동전류가 150[A]이었다. 여기에 Y-$\\Delta$ 기동시 기동전류는 [A]가 되는가?",
    "c1": "50",
    "c2": "70",
    "c3": "87",
    "c4": "95",
    "has_image": false
  },
  {
    "number": 39,
    "q": "다음 중 SCR의 기호는?",
    "c1": "[그림]",
    "c2": "[그림]",
    "c3": "[그림]",
    "c4": "[그림]",
    "has_image": true
  },
  {
    "number": 40,
    "q": "보호 계전기의 기능상 분류로 틀린 것은?",
    "c1": "자동 계전기",
    "c2": "보조 계전기",
    "c3": "리클로저 계전기",
    "c4": "차단 계전기",
    "has_image": false
  },
  {
    "number": 41,
    "q": "옥외용 비닐 절연 전선의 약호(기호)는?",
    "c1": "VW",
    "c2": "NR",
    "c3": "OW",
    "c4": "OC",
    "has_image": false
  },
  {
    "number": 42,
    "q": "변압기(변압기)로 보호 및 개폐할 때 사용되는 특고압 측의 차단기의 정격전류 용량은?",
    "c1": "100[kVA]",
    "c2": "200[kVA]",
    "c3": "수시의 전류 / 변압기 정격[kV] 용량의 20배 이상의 것",
    "c4": "300[kVA]",
    "has_image": false
  },
  {
    "number": 43,
    "q": "접지 단면적 및 특별 제3종 접지사이의 검지저항 접지선의 단면적은 몇 [$\\text{mm}^2$]이상이어야 하는가?",
    "c1": "2.5",
    "c2": "4",
    "c3": "6",
    "c4": "16",
    "has_image": false
  },
  {
    "number": 44,
    "q": "부식성 가스 등이 있는 장소에 시설할 수 없는 배선은?",
    "c1": "에자사용 배선",
    "c2": "제1종 금속제 가요전선관 배선",
    "c3": "라이팅 덕트 배선",
    "c4": "금속 덕트 배선",
    "has_image": false
  },
  {
    "number": 45,
    "q": "학교와 저장소 안에는 백열전등의 점등용 또는 이용등의 점등용 또는 전기를 유도하는 모든 전기설비나 전기기계의 접지저항 값[$\\Omega$] 이하여야 하는가?",
    "c1": "100[V]",
    "c2": "200[V]",
    "c3": "300[V]",
    "c4": "400[V]",
    "has_image": false
  },
  {
    "number": 46,
    "q": "특별 제3종 접지사업의 접지 저항 값은 몇 [$\\Omega$]이하여야 하는가?",
    "c1": "10",
    "c2": "15",
    "c3": "20",
    "c4": "100",
    "has_image": false
  },
  {
    "number": 47,
    "q": "교통 신호등을 설치할 금속체 외함에는 몇 종 접지 공사를 해야 하는가?",
    "c1": "제1종 접지공사",
    "c2": "제2종 접지공사",
    "c3": "제3종 접지공사",
    "c4": "특별 제3종 접지공사",
    "has_image": false
  },
  {
    "number": 48,
    "q": "물장내 수중조명등에 사용되는 절연변압기 1차 및 2차 권선의 사이의 절연내력 금속 흡수판 또는 혼합방사(기)인 것의 접지공사는?",
    "c1": "제1종 접지공사",
    "c2": "제2종 접지공사",
    "c3": "제3종 접지공사",
    "c4": "특별 제3종 접지공사",
    "has_image": false
  },
  {
    "number": 49,
    "q": "진열장 안에 400[V]이면의 기구인 저압 옥내배선의 사이인 몇 [mm]이상의 코드 또는 캡타이어케이블이어야 하는가?",
    "c1": "0.75[mm]",
    "c2": "1.25[mm]",
    "c3": "2[mm]",
    "c4": "3.5[mm]",
    "has_image": false
  },
  {
    "number": 50,
    "q": "금속관에 나사를 내기 위한 공구는?",
    "c1": "오스터",
    "c2": "토치램프",
    "c3": "편치",
    "c4": "유압식 벤더",
    "has_image": false
  },
  {
    "number": 51,
    "q": "내온 공전기를 사용하는 목적은?",
    "c1": "주파수 측정",
    "c2": "전 측정용",
    "c3": "절연 측정",
    "c4": "초도표시",
    "has_image": false
  },
  {
    "number": 52,
    "q": "설비용량 600[kW], 부등률 1.2, 수용률 0.6일 때 합성최대전력[kW]은?",
    "c1": "240[kW]",
    "c2": "300[kW]",
    "c3": "432[kW]",
    "c4": "833[kW]",
    "has_image": false
  },
  {
    "number": 53,
    "q": "경질비닐전선관 1본의 표준 길이는?",
    "c1": "3[m]",
    "c2": "4[m]",
    "c3": "3.5[m]",
    "c4": "4.6[m]",
    "has_image": false
  },
  {
    "number": 54,
    "q": "사람이 접촉할 우려가 있는 곳에 시설하는 경우 접지극은 지하 몇 [cm] 이상의 길이에 매설하여야 하는가?",
    "c1": "30",
    "c2": "45",
    "c3": "50",
    "c4": "75",
    "has_image": false
  },
  {
    "number": 55,
    "q": "480[V] 가공인입선이 철도를 횡단할 때 레일면상의 최저 높이는 몇 [m] 인가?",
    "c1": "4[m]",
    "c2": "5[m]",
    "c3": "5.5[m]",
    "c4": "6.5[m]",
    "has_image": false
  },
  {
    "number": 56,
    "q": "가공 연선 인입선에서 분기 하는 경우(옥외)에서 분기하는 경로부터의 분기가 넘어가 도로를 횡단하지 않을 때, 폭 몇 [m]를 넘는 도로를 횡단하지 않을 때 하여야 하는가?",
    "c1": "50[m], 4[m]",
    "c2": "100[m], 5[m]",
    "c3": "150[m], 6[m]",
    "c4": "200[m], 8[m]",
    "has_image": false
  },
  {
    "number": 57,
    "q": "합성수지 제거기의 기온전선관으로 본 취급이라 다음 중 적절하지 않은 것은?",
    "c1": "PVC전선관과 PF관에 사용",
    "c2": "후강전선관에 별강장치 사용",
    "c3": "PF전선관과 CD관에 사용",
    "c4": "PF전선관과 CD관에 사용",
    "has_image": false
  },
  {
    "number": 58,
    "q": "케이블을 구부리는 경우에는 손상되기 않도록 해야 한다. 그 구부리는 곡률반경은 원칙적으로 케이블이 완성품의 외경 몇 배 이상이어야 하는가?",
    "c1": "6",
    "c2": "8",
    "c3": "10",
    "c4": "12",
    "has_image": false
  },
  {
    "number": 59,
    "q": "재사용에서의 거리(접근에서거의 전선을 이상으로 하여야 하는가?",
    "c1": "2[cm]",
    "c2": "4[cm]",
    "c3": "6[cm]",
    "c4": "8[cm]",
    "has_image": false
  },
  {
    "number": 60,
    "q": "절연전선을 쓸 금속 금구에서의 내에 넣고 절연에 대한 전선의 피복절연물을 포함한 단면적의 총합계가 관 내의 단면적의 몇 [%] 이하이어야 하는가?",
    "c1": "30[%]",
    "c2": "40[%]",
    "c3": "48[%]",
    "c4": "56[%]",
    "has_image": false
  }
]
