{
  "questions": [
    {
      "n": 31,
      "q": "변압기에 콘서베이터(Conservator)를 설치하는 목적은?",
      "c1": "열화 방지",
      "c2": "코로나 방지",
      "c3": "강제 순환",
      "c4": "통풍 장치",
      "a": 1
    },
    {
      "n": 32,
      "q": "정격출력 20[kVA], 정격전압에서의 철손 150[W], 정격전류에서 동손 200[W]의 단상변압기에 뒤진 역률 0.8인 어느 부하를 걸었을 경우 효율이 최대라 한다. 이 때 부하율은 약 몇 [%]인가?",
      "c1": "75",
      "c2": "87",
      "c3": "90",
      "c4": "97",
      "a": 2
    },
    {
      "n": 33,
      "q": "변압기유가 구비해야 할 조건 중 맞는 것은?",
      "c1": "절연 내력이 작고 산화하지 않을 것",
      "c2": "비열이 작아서 냉각 효과가 클 것",
      "c3": "인화점이 높고 응고점이 낮을 것",
      "c4": "절연재료나 금속에 접촉할 때 화학작용을 일으킬 것",
      "a": 3
    },
    {
      "n": 34,
      "q": "역률과 효율이 좋아서 가정용 선풍기, 전기세탁기, 냉장고 등에 주로 사용되는 것은?",
      "c1": "분상 기동형전동기",
      "c2": "반발 기동형전동기",
      "c3": "콘덴서 기동형전동기",
      "c4": "셰이딩 코일형전동기",
      "a": 3
    },
    {
      "n": 35,
      "q": "변압기 내부고장 시 급격한 유류 또는 Gas의 이동이 생기면 동작하는 부흐홀츠 계전기의 설치 위치는?",
      "c1": "변압기 본체",
      "c2": "변압기의 고압측 부싱",
      "c3": "콘서베이터 내부",
      "c4": "변압기 본체와 콘서베이터를 연결하는 파이프",
      "a": 4
    },
    {
      "n": 36,
      "q": "50[Hz], 슬립 0.2인 경우의 회전자 속도가 600[rpm]이 되는 유도전동기의 극수는?",
      "c1": "16극",
      "c2": "12극",
      "c3": "8극",
      "c4": "4극",
      "a": 3
    },
    {
      "n": 37,
      "q": "3상 농형 유도전동기의 Y-$\\Delta$ 기동 시의 기동전류를 전전압기동시와 비교하면?",
      "c1": "전전압 기동전류의 $\\dfrac{1}{3}$로 된다.",
      "c2": "전전압 기동전류의 $\\sqrt{3}$배로 된다.",
      "c3": "전전압 기동전류의 3배로 된다.",
      "c4": "전전압 기동전류의 9배로 된다.",
      "a": 1
    },
    {
      "n": 38,
      "q": "단상유도전동기의 정회전 슬립이 $s$면 역회전 슬립은 어떻게 되는가?",
      "c1": "$1 - s$",
      "c2": "$2 - s$",
      "c3": "$1 + s$",
      "c4": "$2 + s$",
      "a": 2
    },
    {
      "n": 39,
      "q": "10[kw]의 농형 유도전동기의 기동 방법으로 가장 적당한 것은?",
      "c1": "전전압 기동법",
      "c2": "Y-$\\Delta$ 기동법",
      "c3": "기동 보상기법",
      "c4": "2차 저항 기동법",
      "a": 2
    },
    {
      "n": 40,
      "q": "사용 중인 변류기의 2차를 개방하면?",
      "c1": "1차 전류가 감소한다.",
      "c2": "2차 권선에 110[V]가 걸린다.",
      "c3": "개방단의 전압은 불변하고 안전하다.",
      "c4": "2차 권선에 고압이 유도된다.",
      "a": 4
    },
    {
      "n": 41,
      "q": "다음 중 전선이 구비해야 될 조건으로 틀린 것은?",
      "c1": "도전율이 클 것",
      "c2": "기계적인 강도가 강할 것",
      "c3": "비중이 클 것",
      "c4": "내구성이 있을 것",
      "a": 3
    },
    {
      "n": 42,
      "q": "저압 가공 전선이 철도 또는 궤도를 횡단하는 경우에는 레일면상 몇 [m] 이상이어야 하는가?",
      "c1": "3.5",
      "c2": "4.5",
      "c3": "5.5",
      "c4": "6.5",
      "a": 4
    },
    {
      "n": 43,
      "q": "옥내배선공사 중 금속관공사에 사용되는 공구의 설명 중 잘못된 것은?",
      "c1": "전선관의 굽힘 작업에 사용하는 공구는 토치램프나 스프링 벤더를 사용한다.",
      "c2": "전선관의 나사를 내는 작업에 오스터를 사용한다.",
      "c3": "전선관을 절단하는 공구에는 쇠톱 또는 파이프 커터를 사용한다.",
      "c4": "아웃렛 박스의 천공작업에 사용되는 공구는 녹아웃펀치를 사용한다.",
      "a": 1
    },
    {
      "n": 44,
      "q": "접지저항 측정방법으로 가장 적당한 것은?",
      "c1": "절연저항계",
      "c2": "전력계",
      "c3": "교류의 전압, 전류계",
      "c4": "콜라우시 브리지",
      "a": 4
    },
    {
      "n": 45,
      "q": "전선 약호가 CN-CV-W인 케이블의 품명은?",
      "c1": "동심중성선 수밀형 전력케이블",
      "c2": "동심중성선 차수형 전력케이블",
      "c3": "동심중성선 수밀형 저독성 난연 전력케이블",
      "c4": "동심중성선 차수형 저독성 난연 전력케이블",
      "a": 1
    },
    {
      "n": 46,
      "q": "금속전선관을 구부릴 때 금속관의 단면이 심하게 변형되지 않도록 구부려야 하며 일반적으로 그 안측의 반지름은 관 안지름의 몇 배 이상이 되어야 하는가?",
      "c1": "2배",
      "c2": "4배",
      "c3": "6배",
      "c4": "8배",
      "a": 3
    },
    {
      "n": 47,
      "q": "정션 박스 내에서 절연전선을 쥐꼬리 접속한 후 접속과 절연을 위해 사용되는 재료는?",
      "c1": "링형 슬리브",
      "c2": "S형 슬리브",
      "c3": "와이어 커넥터",
      "c4": "터미널 러그",
      "a": 3
    },
    {
      "n": 48,
      "q": "옥내배선공사할 때 연동선을 사용할 경우 전선의 최소 굵기 [mm$^2$] 는?",
      "c1": "1.5",
      "c2": "2.5",
      "c3": "4",
      "c4": "6",
      "a": 2
    },
    {
      "n": 49,
      "q": "애자사용공사에서 전선의 지지점 간의 거리는 전선을 조영재의 윗면 또는 옆면에 따라 붙이는 경우에는 몇 [m] 이하인가?",
      "c1": "1",
      "c2": "2",
      "c3": "2.5",
      "c4": "3",
      "a": 2
    },
    {
      "n": 50,
      "q": "합성수지제 가요전선관(PF관 및 CD관)의 호칭에 포함되지 않는 것은?",
      "c1": "16",
      "c2": "28",
      "c3": "38",
      "c4": "42",
      "a": 3
    },
    {
      "n": 51,
      "q": "금속몰드배선의 사용전압은 몇 [V] 미만이어야 하는가?",
      "c1": "150",
      "c2": "220",
      "c3": "400",
      "c4": "600",
      "a": 3
    },
    {
      "n": 52,
      "q": "연피 케이블이 구부러지는 곳은 케이블 바깥지름의 최소 몇 배 이상의 반지름으로 구부려야 하는가?",
      "c1": "8",
      "c2": "12",
      "c3": "15",
      "c4": "20",
      "a": 2
    },
    {
      "n": 53,
      "q": "접지저항 저감 대책이 아닌 것은?",
      "c1": "접지봉의 연결 개수를 증가시킨다.",
      "c2": "접지판의 면적을 감소시킨다.",
      "c3": "접지극을 깊게 매설한다.",
      "c4": "토양의 고유저항을 화학적으로 저감시킨다.",
      "a": 2
    },
    {
      "n": 54,
      "q": "금속전선관공사에서 금속관과 접속함을 접속하는 경우 녹아웃 구멍이 금속관보다 클 때 사용하는 부품은?",
      "c1": "록너트",
      "c2": "부싱",
      "c3": "새들",
      "c4": "링 리듀서",
      "a": 4
    },
    {
      "n": 55,
      "q": "한국전기설비규정에서 정격전류가 63[A] 이하인 저압전로의 과전류차단기를 주택용 배선용차단기로 사용하는 경우 정격전류의 1.45배의 전류가 통과하였을 경우 몇 분 이내에 자동적으로 동작하여야 하는가?",
      "c1": "30분",
      "c2": "240분",
      "c3": "60분",
      "c4": "120분",
      "a": 3
    },
    {
      "n": 56,
      "q": "일반적으로 가공전선로의 지지물에 취급자가 오르고 내리는 데 사용하는 발판볼트 등은 지표상 몇 [m] 미만에 시설하여서는 아니 되는가?",
      "c1": "0.75[m]",
      "c2": "1.2[m]",
      "c3": "1.8[m]",
      "c4": "2.0[m]",
      "a": 3
    },
    {
      "n": 57,
      "q": "배전용기구인 COS(컷아웃스위치)의 용도로 알맞은 것은?",
      "c1": "배전용 변압기의 1차 측에 시설하여 변압기의 단락보호용으로 쓰인다.",
      "c2": "배전용 변압기의 2차 측에 시설하여 변압기의 단락보호용으로 쓰인다.",
      "c3": "배전용 변압기의 1차 측에 시설하여 배전 구역 전환용으로 쓰인다.",
      "c4": "배전용 변압기의 2차 측에 시설하여 배전 구역 전환용으로 쓰인다.",
      "a": 1
    },
    {
      "n": 58,
      "q": "옥내에 시설하는 저압의 이동 전선에서 사용하는 캡타이어케이블의 최소 단면적으로 옳은 것은?",
      "c1": "0.75[mm$^2$]",
      "c2": "1[mm$^2$]",
      "c3": "1.5[mm$^2$]",
      "c4": "2.5[mm$^2$]",
      "a": 1
    },
    {
      "n": 59,
      "q": "각 수용가의 최대 수용전력이 각각 5[kW], 10[kW], 15[kW], 22[kW]이고, 합성최대수용전력이 50[kW]이다. 수용가 상호 간의 부등률은 얼마인가?",
      "c1": "1.04",
      "c2": "2.34",
      "c3": "4.25",
      "c4": "6.94",
      "a": 1
    },
    {
      "n": 60,
      "q": "부식성 가스 등이 있는 장소에 전기설비를 시설하는 방법으로 적합하지 않은 것은?",
      "c1": "애자사용배선 시 부식성 가스의 종류에 따라 절연 전선인 DV전선을 사용한다.",
      "c2": "애자사용배선에 의한 경우에는 사람이 쉽게 접촉될 우려가 없는 노출장소에 한 한다.",
      "c3": "애자사용배선 시 부득이 나전선을 사용하는 경우에는 전선과 조영재와의 거리를 4.5[cm] 이상으로 한다.",
      "c4": "애자사용배선 시 전선의 절연물이 상해를 받는 장소는 나전선을 사용할 수 있으며, 이 경우는 바닥 위 2.5[m] 이상 높이에 시설한다.",
      "a": 1
    }
  ]
}
